{"version":2.92,"type":"NodeCanvas.BehaviourTrees.BehaviourTree","translation":{"x":-224.0,"y":46.0},"nodes":[{"_condition":{"conditions":[{"QuestEventRef":{"m_eventUID":"1nGk1TyMbUi3VmSdn32zCg"},"$type":"NodeCanvas.Tasks.Conditions.Condition_QuestEventOccured"},{"QuestEventRef":{"m_eventUID":"Kp716bN-p0ODGUe1_Sp5-g"},"_invert":true,"$type":"NodeCanvas.Tasks.Conditions.Condition_QuestEventOccured"},{"QuestEventRef":{"m_eventUID":"SA0XvrfRGkWZRfRmk19V2g"},"$type":"NodeCanvas.Tasks.Conditions.Condition_QuestEventOccured"},{"QuestEventRef":{"m_eventUID":"0bj5S2Z3Z022_7Ke0D5-OA"},"$type":"NodeCanvas.Tasks.Conditions.Condition_QuestEventOccured"}],"$type":"NodeCanvas.Framework.ConditionList"},"_color":{"r":0.7019608,"g":1.0,"b":0.4980392,"a":1.0},"_position":{"x":480.0,"y":60.0},"$type":"NodeCanvas.BehaviourTrees.BinarySelector","$id":"2"},{"_action":{"Target":{"_value":1,"_name":"Immaculate Negociator","_targetVariableID":"f2ee3fb9-186e-4306-ae43-6e8af4ae33dc"},"IsActive":{"_value":true},"$type":"NodeCanvas.Tasks.Actions.SetActiveGameObject"},"_position":{"x":255.0,"y":315.0},"$type":"NodeCanvas.BehaviourTrees.ActionNode","$id":"13"},{"_condition":{"conditions":[{"QuestEventRef":{"m_eventUID":"1nGk1TyMbUi3VmSdn32zCg"},"$type":"NodeCanvas.Tasks.Conditions.Condition_QuestEventOccured"},{"QuestEventRef":{"m_eventUID":"Kp716bN-p0ODGUe1_Sp5-g"},"_invert":true,"$type":"NodeCanvas.Tasks.Conditions.Condition_QuestEventOccured"},{"QuestEventRef":{"m_eventUID":"SA0XvrfRGkWZRfRmk19V2g"},"$type":"NodeCanvas.Tasks.Conditions.Condition_QuestEventOccured"},{"QuestEventRef":{"m_eventUID":"DSooGqQNTEK7YXR8d71cJg"},"$type":"NodeCanvas.Tasks.Conditions.Condition_QuestEventOccured"}],"$type":"NodeCanvas.Framework.ConditionList"},"_color":{"r":0.7019608,"g":1.0,"b":0.4980392,"a":1.0},"_position":{"x":750.0,"y":285.0},"$type":"NodeCanvas.BehaviourTrees.BinarySelector","$id":"17"},{"_action":{"Target":{"_value":1,"_name":"Immaculate Negociator","_targetVariableID":"f2ee3fb9-186e-4306-ae43-6e8af4ae33dc"},"IsActive":{},"$type":"NodeCanvas.Tasks.Actions.SetActiveGameObject"},"_position":{"x":525.0,"y":525.0},"$type":"NodeCanvas.BehaviourTrees.ActionNode","$id":"28"},{"_condition":{"conditions":[{"QuestEventRef":{"m_eventUID":"1nGk1TyMbUi3VmSdn32zCg"},"$type":"NodeCanvas.Tasks.Conditions.Condition_QuestEventOccured"},{"QuestEventRef":{"m_eventUID":"Kp716bN-p0ODGUe1_Sp5-g"},"_invert":true,"$type":"NodeCanvas.Tasks.Conditions.Condition_QuestEventOccured"},{"QuestEventRef":{"m_eventUID":"SA0XvrfRGkWZRfRmk19V2g"},"$type":"NodeCanvas.Tasks.Conditions.Condition_QuestEventOccured"}],"$type":"NodeCanvas.Framework.ConditionList"},"_color":{"r":0.7019608,"g":1.0,"b":0.4980392,"a":1.0},"_position":{"x":1005.0,"y":495.0},"$type":"NodeCanvas.BehaviourTrees.BinarySelector","$id":"32"},{"_action":{"Target":{"_value":1,"_name":"Immaculate Negociator","_targetVariableID":"f2ee3fb9-186e-4306-ae43-6e8af4ae33dc"},"IsActive":{"_value":true},"$type":"NodeCanvas.Tasks.Actions.SetActiveGameObject"},"_position":{"x":825.0,"y":675.0},"$type":"NodeCanvas.BehaviourTrees.ActionNode","$id":"41"},{"_action":{"Target":{"_value":1,"_name":"Immaculate Negociator","_targetVariableID":"f2ee3fb9-186e-4306-ae43-6e8af4ae33dc"},"IsActive":{},"$type":"NodeCanvas.Tasks.Actions.SetActiveGameObject"},"_position":{"x":1275.0,"y":675.0},"$type":"NodeCanvas.BehaviourTrees.ActionNode","$id":"45"}],"connections":[{"_sourceNode":{"$ref":"2"},"_targetNode":{"$ref":"13"},"$type":"NodeCanvas.BehaviourTrees.BTConnection"},{"_sourceNode":{"$ref":"2"},"_targetNode":{"$ref":"17"},"$type":"NodeCanvas.BehaviourTrees.BTConnection"},{"_sourceNode":{"$ref":"17"},"_targetNode":{"$ref":"28"},"$type":"NodeCanvas.BehaviourTrees.BTConnection"},{"_sourceNode":{"$ref":"17"},"_targetNode":{"$ref":"32"},"$type":"NodeCanvas.BehaviourTrees.BTConnection"},{"_sourceNode":{"$ref":"32"},"_targetNode":{"$ref":"41"},"$type":"NodeCanvas.BehaviourTrees.BTConnection"},{"_sourceNode":{"$ref":"32"},"_targetNode":{"$ref":"45"},"$type":"NodeCanvas.BehaviourTrees.BTConnection"}],"localBlackboard":{"_name":"Local Blackboard","_variables":{}},"derivedData":{"$type":"NodeCanvas.BehaviourTrees.BehaviourTree+DerivedSerializationData"}}
