{"version":2.92,"type":"NodeCanvas.BehaviourTrees.BehaviourTree","translation":{"x":-6563.937,"y":-4365.959},"nodes":[{"_position":{"x":6701.0,"y":4769.0},"$type":"NodeCanvas.BehaviourTrees.Parallel","$id":"2"},{"_condition":{"QuestEventRef":{"m_eventUID":"gSCCl5ZSXkC-2awJWrCAFw"},"$type":"NodeCanvas.Tasks.Conditions.Condition_QuestEventOccured"},"_position":{"x":6338.0,"y":5027.0},"$type":"NodeCanvas.BehaviourTrees.BinarySelector","$id":"3"},{"_condition":{"QuestEventRef":{"m_eventUID":"A2Yt2GByhkudG_UG55-xPQ"},"$type":"NodeCanvas.Tasks.Conditions.Condition_QuestEventOccured"},"_color":{"r":0.7019608,"g":1.0,"b":0.4980392,"a":1.0},"_position":{"x":6036.0,"y":5140.0},"$type":"NodeCanvas.BehaviourTrees.BinarySelector","$id":"6"},{"_action":{"actions":[{"setTo":"Activate","overrideAgent":{"_name":"CrimsonOpen","_targetVariableID":"c833e0c6-fed3-4bef-be7e-d5ed59580a51"},"$type":"NodeCanvas.Tasks.Actions.SetObjectActive"},{"setTo":"Deactivate","overrideAgent":{"_name":"CrimsonClosed","_targetVariableID":"11570693-8b38-4cda-b0bd-c2d5544373c9"},"$type":"NodeCanvas.Tasks.Actions.SetObjectActive"}],"$type":"NodeCanvas.Framework.ActionList"},"_position":{"x":5976.0,"y":5269.0},"$type":"NodeCanvas.BehaviourTrees.ActionNode","$id":"9"},{"_action":{"actions":[{"setTo":"Deactivate","overrideAgent":{"_name":"CrimsonOpen","_targetVariableID":"c833e0c6-fed3-4bef-be7e-d5ed59580a51"},"$type":"NodeCanvas.Tasks.Actions.SetObjectActive"},{"setTo":"Activate","overrideAgent":{"_name":"CrimsonClosed","_targetVariableID":"11570693-8b38-4cda-b0bd-c2d5544373c9"},"$type":"NodeCanvas.Tasks.Actions.SetObjectActive"}],"$type":"NodeCanvas.Framework.ActionList"},"_position":{"x":6294.0,"y":5270.0},"$type":"NodeCanvas.BehaviourTrees.ActionNode","$id":"16"},{"_action":{"actions":[{"setTo":"Deactivate","overrideAgent":{"_name":"CrimsonOpen","_targetVariableID":"c833e0c6-fed3-4bef-be7e-d5ed59580a51"},"$type":"NodeCanvas.Tasks.Actions.SetObjectActive"},{"setTo":"Deactivate","overrideAgent":{"_name":"CrimsonClosed","_targetVariableID":"11570693-8b38-4cda-b0bd-c2d5544373c9"},"$type":"NodeCanvas.Tasks.Actions.SetObjectActive"}],"$type":"NodeCanvas.Framework.ActionList"},"_position":{"x":6572.0,"y":5142.0},"$type":"NodeCanvas.BehaviourTrees.ActionNode","$id":"23"},{"_condition":{"QuestEventRef":{"m_eventUID":"0A1tqQKKMkCS1zFrEsGrAw"},"$type":"NodeCanvas.Tasks.Conditions.Condition_QuestEventOccured"},"_position":{"x":7049.0,"y":5005.0},"$type":"NodeCanvas.BehaviourTrees.BinarySelector","$id":"30"},{"_action":{"actions":[{"setTo":"Activate","overrideAgent":{"_name":"DwellerOpen","_targetVariableID":"04238bd0-b1db-4789-8d59-79835474fd03"},"$type":"NodeCanvas.Tasks.Actions.SetObjectActive"},{"setTo":"Deactivate","overrideAgent":{"_name":"DwellerClosed","_targetVariableID":"1f5a2b4a-143d-4e3d-b372-bcf4c2f96c32"},"$type":"NodeCanvas.Tasks.Actions.SetObjectActive"},{"setTo":"Activate","overrideAgent":{"_name":"DwellerFreed","_targetVariableID":"c176602f-0dba-405b-ba3b-c30f471eb845"},"$type":"NodeCanvas.Tasks.Actions.SetObjectActive"}],"$type":"NodeCanvas.Framework.ActionList"},"_position":{"x":6999.0,"y":5119.0},"$type":"NodeCanvas.BehaviourTrees.ActionNode","$id":"33"},{"_action":{"actions":[{"setTo":"Deactivate","overrideAgent":{"_name":"DwellerOpen","_targetVariableID":"04238bd0-b1db-4789-8d59-79835474fd03"},"$type":"NodeCanvas.Tasks.Actions.SetObjectActive"},{"setTo":"Activate","overrideAgent":{"_name":"DwellerClosed","_targetVariableID":"1f5a2b4a-143d-4e3d-b372-bcf4c2f96c32"},"$type":"NodeCanvas.Tasks.Actions.SetObjectActive"},{"setTo":"Deactivate","overrideAgent":{"_name":"DwellerFreed","_targetVariableID":"c176602f-0dba-405b-ba3b-c30f471eb845"},"$type":"NodeCanvas.Tasks.Actions.SetObjectActive"}],"$type":"NodeCanvas.Framework.ActionList"},"_position":{"x":7267.0,"y":5120.0},"$type":"NodeCanvas.BehaviourTrees.ActionNode","$id":"42"},{"_condition":{"QuestEventRef":{"m_eventUID":"Fk-272D_Cke_gCAHTWNTMg"},"MinStack":7,"$type":"NodeCanvas.Tasks.Conditions.Condition_QuestEventOccured"},"_position":{"x":7109.0,"y":4603.0},"$type":"NodeCanvas.BehaviourTrees.BinarySelector","$id":"51"},{"_action":{"setTo":"Activate","overrideAgent":{"_name":"Secret","_targetVariableID":"c1cbc053-c19a-487d-977b-6904b360ff2b"},"$type":"NodeCanvas.Tasks.Actions.SetObjectActive"},"_position":{"x":7086.0,"y":4717.0},"$type":"NodeCanvas.BehaviourTrees.ActionNode","$id":"54"},{"_action":{"setTo":"Deactivate","overrideAgent":{"_name":"Secret","_targetVariableID":"c1cbc053-c19a-487d-977b-6904b360ff2b"},"$type":"NodeCanvas.Tasks.Actions.SetObjectActive"},"_position":{"x":7278.0,"y":4719.0},"$type":"NodeCanvas.BehaviourTrees.ActionNode","$id":"57"}],"connections":[{"_sourceNode":{"$ref":"2"},"_targetNode":{"$ref":"3"},"$type":"NodeCanvas.BehaviourTrees.BTConnection"},{"_sourceNode":{"$ref":"2"},"_targetNode":{"$ref":"30"},"$type":"NodeCanvas.BehaviourTrees.BTConnection"},{"_sourceNode":{"$ref":"2"},"_targetNode":{"$ref":"51"},"$type":"NodeCanvas.BehaviourTrees.BTConnection"},{"_sourceNode":{"$ref":"3"},"_targetNode":{"$ref":"6"},"$type":"NodeCanvas.BehaviourTrees.BTConnection"},{"_sourceNode":{"$ref":"3"},"_targetNode":{"$ref":"23"},"$type":"NodeCanvas.BehaviourTrees.BTConnection"},{"_sourceNode":{"$ref":"6"},"_targetNode":{"$ref":"9"},"$type":"NodeCanvas.BehaviourTrees.BTConnection"},{"_sourceNode":{"$ref":"6"},"_targetNode":{"$ref":"16"},"$type":"NodeCanvas.BehaviourTrees.BTConnection"},{"_sourceNode":{"$ref":"30"},"_targetNode":{"$ref":"33"},"$type":"NodeCanvas.BehaviourTrees.BTConnection"},{"_sourceNode":{"$ref":"30"},"_targetNode":{"$ref":"42"},"$type":"NodeCanvas.BehaviourTrees.BTConnection"},{"_sourceNode":{"$ref":"51"},"_targetNode":{"$ref":"54"},"$type":"NodeCanvas.BehaviourTrees.BTConnection"},{"_sourceNode":{"$ref":"51"},"_targetNode":{"$ref":"57"},"$type":"NodeCanvas.BehaviourTrees.BTConnection"}],"canvasGroups":[{"name":"Crimson Boss entrance","rect":{"xMin":5874.0,"yMin":5000.0,"xMax":6843.0,"yMax":5360.0}},{"name":"DwellerDoor","rect":{"xMin":6963.0,"yMin":4950.0,"xMax":7505.0,"yMax":5248.0}},{"name":"Secret","rect":{"xMin":7074.0,"yMin":4560.0,"xMax":7437.0,"yMax":4825.0}}],"localBlackboard":{"_name":"Local Blackboard","_variables":{}},"derivedData":{"$type":"NodeCanvas.BehaviourTrees.BehaviourTree+DerivedSerializationData"}}
