{"version":2.92,"type":"NodeCanvas.DialogueTrees.DialogueTreeExt","translation":{"x":-6286.0,"y":-6393.0},"nodes":[{"_condition":{"checkMode":"AnyTrueSuffice","conditions":[{"QuestEventRef":{"m_eventUID":"X-AkhlW7wk-CSLm_cEHrJg"},"$type":"NodeCanvas.Tasks.Conditions.Condition_QuestEventOccured"},{"QuestEventRef":{"m_eventUID":"HKTzod7WpEyGqG7zTvvyjA"},"$type":"NodeCanvas.Tasks.Conditions.Condition_QuestEventOccured"}],"$type":"NodeCanvas.Framework.ConditionList"},"_position":{"x":6705.0,"y":6480.0},"$type":"NodeCanvas.DialogueTrees.ConditionNode","$id":"2"},{"_action":{"QuestEventRef":{"m_eventUID":"VAvGhkMCH0mWLqy2DLL2zA"},"$type":"NodeCanvas.Tasks.Actions.SendQuestEvent"},"_position":{"x":6645.0,"y":6615.0},"$type":"NodeCanvas.DialogueTrees.ActionNode","$id":"9"},{"statement":{"_text":"(The arm waves at you. Clearly this belongs to Myriade)","_meta":"Myriade_HM_Questions_26"},"_actorName":"name_unpc_narrator","_actorParameterID":"7cce4164-d690-4c14-ace8-a82fa4d868e8","_position":{"x":6555.0,"y":6720.0},"$type":"NodeCanvas.DialogueTrees.StatementNodeExt","$id":"12"},{"_position":{"x":6915.0,"y":6840.0},"$type":"NodeCanvas.DialogueTrees.FinishNode","$id":"14"},{"_condition":{"checkMode":"AnyTrueSuffice","conditions":[{"QuestEventRef":{"m_eventUID":"X-AkhlW7wk-CSLm_cEHrJg"},"$type":"NodeCanvas.Tasks.Conditions.Condition_QuestEventOccured"},{"QuestEventRef":{"m_eventUID":"HKTzod7WpEyGqG7zTvvyjA"},"$type":"NodeCanvas.Tasks.Conditions.Condition_QuestEventOccured"}],"$type":"NodeCanvas.Framework.ConditionList"},"_position":{"x":6615.0,"y":5925.0},"$type":"NodeCanvas.DialogueTrees.ConditionNode","$id":"15"},{"statement":{"_text":"(The arm waves at you. Clearly this belongs to Myriade)","_meta":"Myriade_HM_Questions_26"},"_actorName":"name_unpc_narrator","_actorParameterID":"7cce4164-d690-4c14-ace8-a82fa4d868e8","_position":{"x":6420.0,"y":6075.0},"$type":"NodeCanvas.DialogueTrees.StatementNodeExt","$id":"22"},{"availableChoices":[{"statement":{"_text":"(Take Myriade\u2019s body part)","_meta":"Player_Myriade_HM_Questions_a_26"}},{"statement":{"_text":"(Leave it be)","_meta":"Player_Myriade_HM_Questions_b_26"}}],"_position":{"x":6390.0,"y":6210.0},"$type":"NodeCanvas.DialogueTrees.MultipleChoiceNodeExt","$id":"24"},{"_action":{"QuestEventRef":{"m_eventUID":"VAvGhkMCH0mWLqy2DLL2zA"},"$type":"NodeCanvas.Tasks.Actions.SendQuestEvent"},"_position":{"x":6270.0,"y":6375.0},"$type":"NodeCanvas.DialogueTrees.ActionNode","$id":"30"},{"_position":{"x":6330.0,"y":6510.0},"$type":"NodeCanvas.DialogueTrees.FinishNode","$id":"33"},{"_position":{"x":6555.0,"y":6345.0},"$type":"NodeCanvas.DialogueTrees.FinishNode","$id":"34"},{"statement":{"_text":"(A badly mangled bone lies here...Whoever this belongs to must have died horribly)","_meta":"Myriade_HM_Questions_25-b"},"_actorName":"name_unpc_narrator","_actorParameterID":"7cce4164-d690-4c14-ace8-a82fa4d868e8","_position":{"x":6870.0,"y":6105.0},"$type":"NodeCanvas.DialogueTrees.StatementNodeExt","$id":"35"},{"_position":{"x":6915.0,"y":6240.0},"$type":"NodeCanvas.DialogueTrees.FinishNode","$id":"37"}],"connections":[{"_sourceNode":{"$ref":"2"},"_targetNode":{"$ref":"9"},"$type":"NodeCanvas.DialogueTrees.DTConnection"},{"_sourceNode":{"$ref":"2"},"_targetNode":{"$ref":"14"},"$type":"NodeCanvas.DialogueTrees.DTConnection"},{"_sourceNode":{"$ref":"9"},"_targetNode":{"$ref":"12"},"$type":"NodeCanvas.DialogueTrees.DTConnection"},{"_sourceNode":{"$ref":"12"},"_targetNode":{"$ref":"14"},"$type":"NodeCanvas.DialogueTrees.DTConnection"},{"_sourceNode":{"$ref":"15"},"_targetNode":{"$ref":"22"},"$type":"NodeCanvas.DialogueTrees.DTConnection"},{"_sourceNode":{"$ref":"15"},"_targetNode":{"$ref":"35"},"$type":"NodeCanvas.DialogueTrees.DTConnection"},{"_sourceNode":{"$ref":"22"},"_targetNode":{"$ref":"24"},"$type":"NodeCanvas.DialogueTrees.DTConnection"},{"_sourceNode":{"$ref":"24"},"_targetNode":{"$ref":"30"},"$type":"NodeCanvas.DialogueTrees.DTConnection"},{"_sourceNode":{"$ref":"24"},"_targetNode":{"$ref":"34"},"$type":"NodeCanvas.DialogueTrees.DTConnection"},{"_sourceNode":{"$ref":"30"},"_targetNode":{"$ref":"33"},"$type":"NodeCanvas.DialogueTrees.DTConnection"},{"_sourceNode":{"$ref":"35"},"_targetNode":{"$ref":"37"},"$type":"NodeCanvas.DialogueTrees.DTConnection"}],"localBlackboard":{"_name":"Local Blackboard","_variables":{"gInstigator":{"_name":"gInstigator","_id":"42e78054-abcd-4268-b9cb-b6cdc9b523e4","$type":"NodeCanvas.Framework.Variable`1[[Character, Assembly-CSharp, Version=0.0.0.0, Culture=neutral, PublicKeyToken=null]]"}}},"derivedData":{"actorParameters":[{"_keyName":"name_unpc_narrator","_id":"7cce4164-d690-4c14-ace8-a82fa4d868e8","_actorObject":1}],"$type":"NodeCanvas.DialogueTrees.DialogueTree+DerivedSerializationData"}}
