{"version":2.92,"type":"NodeCanvas.DialogueTrees.DialogueTreeExt","nodes":[{"statement":{"_text":"NO LOC - Blood MAge lore 2","_meta":"BloodMage_BOOK_SO_SideQuest_02"},"_actorName":"name_object_ancientnote_01","_actorParameterID":"88111778-2f66-458d-b5da-589c8bd16175","_position":{"x":452.0,"y":265.0},"$type":"NodeCanvas.DialogueTrees.StatementNodeExt","$id":"2"},{"_position":{"x":523.0,"y":378.0},"$type":"NodeCanvas.DialogueTrees.FinishNode","$id":"4"}],"connections":[{"_sourceNode":{"$ref":"2"},"_targetNode":{"$ref":"4"},"$type":"NodeCanvas.DialogueTrees.DTConnection"}],"localBlackboard":{"_name":"Local Blackboard","_variables":{}},"derivedData":{"actorParameters":[{"_keyName":"name_object_ancientnote_01","_id":"88111778-2f66-458d-b5da-589c8bd16175","_actorObject":1}],"$type":"NodeCanvas.DialogueTrees.DialogueTree+DerivedSerializationData"}}
